setup.py
qllauncher/__init__.py
qllauncher/launchers.py
qllauncher/qlhandle.py
qllauncher/qlnetwork.py
qllauncher/qlprofile.py
qllauncher/qlxmpp.py
qllauncher/serverbrowser.py
qllauncher.egg-info/PKG-INFO
qllauncher.egg-info/SOURCES.txt
qllauncher.egg-info/dependency_links.txt
qllauncher.egg-info/requires.txt
qllauncher.egg-info/top_level.txt
qllauncher/helpers/__init__.py
qllauncher/helpers/hash.py
qllauncher/helpers/misc.py
qllauncher/helpers/singleton.py
qllauncher/tests/__init__.py
qllauncher/tests/qlprofiletests.py