Metadata-Version: 1.0
Name: qllauncher
Version: 0.6.1.10
Summary: QuakeLive Library implements interaction between QuakeLive network and QuakeLive game client.
Home-page: https://bitbucket.org/fx_/python3-qllauncher
Author: Victor Polevoy
Author-email: contact@vpolevoy.com
License: UNKNOWN
Platform: UNKNOWN
